seatools/ioc/server/__init__.py
seatools/ioc/server/uvicorn/__init__.py
seatools/ioc/server/uvicorn/main.py
seatools_server_uvicorn-1.0.1.dist-info/METADATA
seatools_server_uvicorn-1.0.1.dist-info/WHEEL
seatools_server_uvicorn-1.0.1.dist-info/entry_points.txt
seatools_server_uvicorn-1.0.1.dist-info/licenses/LICENSE
seatools_server_uvicorn-1.0.1.dist-info/RECORD
