Metadata-Version: 2.3
Name: seatools-server-uvicorn
Version: 1.0.1
Summary: Seatools Server Uvicorn
Project-URL: Homepage, https://github.com/seatools-py/seatools-server-uvicorn
Project-URL: Issues, https://github.com/seatools-py/seatools-server-uvicorn/issues
Author-email: seatools-py <521274311@qq.com>
License: MIT
Keywords: seatools,server,uvicorn
Classifier: License :: OSI Approved :: MIT License
Classifier: Operating System :: OS Independent
Classifier: Programming Language :: Python :: 3
Requires-Python: >=3.9
Requires-Dist: click
Requires-Dist: seatools
Requires-Dist: uvicorn[standard]
